{"pages":[{"text":"El conocimiento de la empresa Conceptos previos: Dato Representaci\u00f3n de un grupo de objetos y acontencimientos que suceden en el mundo real. Informaci\u00f3n La materia prima del conocimiento, es un medio necesario para obtener y construir conocimiento. Representa un conjunto de datos estructurados, contextualizados, categorizados, calculados, corregidos y condensados. Conocimiento Es un recurso intangible con un potencial para la construcci\u00f3n de una ventaja competitiva sostenible. Representa verdades y creencias, perspectivas y conceptos, juicios y expectativas, metodolog\u00eda y know how . Capital social o intelectual Esta formado por las relaciones interpersonales y por los recursos involucrados en estas relaciones. Por tanto, incluye un conjunto de recursos intangibles basados en el conocimiento. Dimensiones: Relacional El capital social es el conjunto de recursos ligados a las relaciones entre individuos de la empresa, y de estos con otros stakeholders Elementos esenciales: Lenguaje y experiencias Normas y sanciones Expectativas Obligaciones Estructural El capital social es todo el conocimiento que queda en la empresa (bases de datos, rutinas, estrategias o cultura organizativa) Humana Representa la acumulaci\u00f3n de conocimiento individual de todos los recursos humanos de la empresa. La creaci\u00f3n del conocimiento La gesti\u00f3n del conocimiento e Bilbao, Escudero y Rodriguez, Pol\u00edtica de Empresa y Estrategia , Cap\u00edtulo 13: La visi\u00f3n del empresa basada en el conocimiento, 3\u00aaEd 2013, Editorial Universitas","tags":"uned","loc":"/dimesion-estrategica-conocimiento.html","title":"Dimensi\u00f3n estrat\u00e9gica del conocimiento"},{"text":"Activo financiero al coste amortizado 2004 Para preparar el balace consolidado: 175 Resultado del ejercicio a Valores representativos a lp 175 Para preparar la cta. PyG consolidada: 175 Beneficios en participaciones y valores representativos de deuda a Saldo de P\u00e9rdidas y Ganancias 175 2005 Para preparar el balance consolidado: 175 Reservas a Valores representativos de deuda a lp 91 a Resultado del ejercicio 84 Para preparar la cta. de PYG: 84 Saldo de PyG a Ingresos de valores representativos de deuda 84","tags":"misc","loc":"/eliminacion-resultados.html","title":"Eliminaci\u00f3n de resultados por operaciones internas"},{"text":"Introducci\u00f3n Clasificaci\u00f3n de estrategias b\u00e1sicas: (Ansoff, 1977) Productos Tradicionales Productos Nuevos Mercados Tradicionales EXPANSI\u00d3N Penetraci\u00f3n en el mercado EXPANSI\u00d3N Desarrollo de productos Mercados Nuevos EXPANSI\u00d3N Desarrollo de mercados DIVERSIFICACI\u00d3N Fundamentos de la Estrategia de Internacionalizaci\u00f3n \u00bfPorque y c\u00f3mo se internacionaliza la empresa? Razones Raz\u00f3n general La adaptaci\u00f3n a un entorno cada vez m\u00e1s global. Factores Pais Ciclo de vida del producto o de la industria Cuando en el pa\u00eds de origen empiezan a notarse las fases de madurez, las empresas pueden buscar mercados extranjeros que se encuentren en una fase anterior. Puede ser suficiente la existencia de una demanda fuerte en un pa\u00eds extranjero. Reducci\u00f3n de costes Sin entrar en cuestiones \u00e9ticas, muchas veces, la internacionalizaci\u00f3n responde a la busqueda de condiciones favorables respecto a los distintos inputs. Tama\u00f1o m\u00ednimo eficiente Si hay econom\u00edas de escala, es posible que la demanda local no sea suficiente para alcanzar un nivel aceptable de eficiencia, por lo que procura una estrategia de internacionalizaci\u00f3n en busca de aumentar la demanda. Ej: Heineken, Carlsberg y Guiness B\u00fasqueda de recursos Condiciones legales Factores del Sector Nivel de globalizaci\u00f3n: Porter, distingue los sectores, seg\u00fan el grado de globalizaci\u00f3n , en dos extremos: Industrias multipa\u00eds La competencia en cada pa\u00eds es independiente del resto. Las empresas tendr\u00e1n que adaptarse a las condiciones propias de cada mercado. La internacionalizaci\u00f3n es opcional Industrias globales El sector, a nivel internacional, est\u00e1 formado por una serie de subsectores nacionales. Las empresas compiten a nivel global. La internacionalizaci\u00f3n es inevitable Factores de la Empresa Exceso de recursos Reducci\u00f3n del riesgo global de la compa\u00f1\u00eda Dependencia estrat\u00e9gica Opciones Porter, partiendo del modelo de la cadena de valor distingue entre: Actividades orientadas hacia abajo (Cliente) Actividades orientadas hacia arriba (Proveedor) La estrategia internacional de las empresas depender\u00e1 de dos decisiones: De configuraci\u00f3n (localizaci\u00f3n de las actividades que componen la cadena de valor) y de nivel de coordinaci\u00f3n entre dichas actividades. Coordinaci\u00f3n Alta Multipais Coordinada Global Pura Baja Multipais Pura Global con adaptaciones Dispersi\u00f3n Concentraci\u00f3n Configuraci\u00f3n Estrategia Global La coordinaci\u00f3n y la configuraci\u00f3n tienden a ser m\u00e1ximas Las empresas tratan de competir en costes sin perseguir la adaptaci\u00f3n al cliente. Estrategia Global con adaptaciones Las empresas sacrifican parte de la eficiencia basada en la estandarizaci\u00f3n para adaptarse a los distintos mercados. Estrategia Multipais Las filiales funcionan de forma semiaut\u00f3noma Las empresas comparten algunan capacidades que poseen a nivel global Es la peor situaci\u00f3n desde el punto de vista de la eficiencia Estrategia Multipais Coordinada Localizar las actividades hacia arriba para optimizar los costes Localizar las actividades hacia abajo m\u00e1s cerca de los clientes Esta estrategia implica unos costes muy elevados derivados de la alta coordinaci\u00f3n y dispersi\u00f3n. La evoluci\u00f3n de las industrias tiende a la globalizaci\u00f3n. Esto tiene una doble implicaci\u00f3n. Las empresas tratar\u00e1n de conseguir altos niveles de coordinaci\u00f3n. Sin embargo, la concentraci\u00f3n tiene l\u00edmites, por lo que las empresas deber\u00e1n concebir su estrategia internacional de un modo din\u00e1mico. Formas (Modelo de Uppsala) Tres opciones fundamentales: Operaciones comerciales (Importaci\u00f3n / Exportaci\u00f3n) Acuerdos contractuales (Joint-ventures, Alianzas, Licencias) Inversi\u00f3n Directa Exterior El modelo percibe la internacionalizaci\u00f3n como un proceso en el que la empresa incrementa gradualmente su compromiso internacional. El proceso evoluciona en funci\u00f3n de dos variables: Desarrollo de conocimientos Cantidad de Recursos comprometidos Dos aspectos sobre el Modelo de Uppsala: Describe como el compromiso en un mercado se desarrolla siguiendo unas pautas: La entrada se realiza al principio a trav\u00e9s de exportaciones irregulares La siguiente fase implica la utilizaci\u00f3n de agentes independientes Finalmente, mediante la IDE a trav\u00e9s de filiales comerciales y/o productivas Explica la elecci\u00f3n del pa\u00eds de destino Donde las distancias geogr\u00e1fica y psicologica (idioma, cultura, desarrollo...) sean menores Ghemawat describe cuatro tipos de distancia ( modelo CAGE ) Distancia C ultural: Idioma, Raza, Religi\u00f3n, Normas sociales... Distancia A dministrativa: Lazos coloniales, Asociaciones pol\u00edticas, Hostilidad pol\u00edtica... Distancia G eogr\u00e1fica: Lejan\u00eda, Frontera com\u00fan, Acceso fluvial, Medios de transporte... Distancia E con\u00f3mica: Dif en los ingresos de los clientes, dif en costes y calidad de inputs... Precisiones: Su aplicaci\u00f3n est\u00e1 orientada para empresas peque\u00f1as El modelo se ajusta mejor a empresas sin experiencia previa en la actividad internacional Empresas grandes y las que tienen mayor experiencia alterar\u00e1n el patr\u00f3n descrito por el modelo de Uppsala Estrategia de diversificaci\u00f3n Diversificaci\u00f3n relacionada Integraci\u00f3n vertical Resultados de la estrategia de diversificaci\u00f3n","tags":"estrategia","loc":"/estrategias-corportativas-crecimiento.html","title":"Estrategias corporativas de crecimiento: Internacionalizaci\u00f3n y Diversificaci\u00f3n"},{"text":"Resulta que hace unos d\u00edas decid\u00ed probar el terminal Guake y cada vez que lo uso me gusta m\u00e1s, sin embargo, siempre que pulsaba Ctrl + Alt + T, se abr\u00eda la antigua terminal que gnome trae de serie. Para cambiar la configuraci\u00f3n de gnome abrir una terminal y ejecutar el siguiente comando: gsettings set org.gnome.desktop.default-applications.terminal exec 'guake' Ahora siempre aparecer\u00e1 guake cuando invoquemos la terminal, y recuerda para enconderla y volverla a llamar con F12","tags":"Linux","loc":"/cambiar-terminal-gnome.html","title":"Como cambiar la Terminal por defecto de gnome"},{"text":"This is the content of my super blog post. $e&#94;2=\\dfrac{\\int_0&#94;\\infty dx}{4}$ Prueba de ipython In [1]: for n in range ( 10 ): print n 0 1 2 3 4 5 6 7 8 9 In []: for n in range ( 10 ): print n In [47]: #!/bin/python import matplotlib.pyplot as plt import seaborn as sns import pandas as pd In [48]: # Datos para generar el mapa de estabilidad financiera mundial. # Fuente: Publicaci\u00f3n semestral GFSR del FMI # Etiquetas riesgos = [ 'Riesgos de mercados emergentes' , 'Riesgos de cr\u00e9dito' , 'Riesgos de mercado y liquidez' , 'Apetito de riesgo' , 'Condiciones monetarias y financieras' , 'Riesgos macroecon\u00f3micos' ] # \u00cdndice de la serie temporal ix = [ '1/4/2007' , '1/10/2007' , '1/4/2008' , '1/10/2008' , '1/4/2009' , '1/10/2009' , '1/4/2010' , '1/10/2010' , '1/4/2011' , '1/10/2011' , '1/4/2012' , '1/10/2012' , '1/4/2013' , '1/10/2013' ] ix = [ pd . to_datetime ( d , dayfirst = True ) for d in ix ] # Datos em = [ 3.0 , 3.0 , 5.0 , 6.0 , 8.9 , 6.9 , 5.9 , 5.0 , 4.0 , 5.0 , 5.0 , 6.0 , 5.0 , 6.0 ] # Riesgos de mercados emergentes ml = [ 4.0 , 6.0 , 7.0 , 9.0 , 9.0 , 7.0 , 6.0 , 6.0 , 6.0 , 6.9 , 6.0 , 5.9 , 4.0 , 5.0 ] # Riesgos de mercado y liquidez mr = [ 3.0 , 4.0 , 7.0 , 8.0 , 9.0 , 8.0 , 7.0 , 7.9 , 6.1 , 7.0 , 7.0 , 8.0 , 7.0 , 7.0 ] # Riesgos macroecon\u00f3micos mf = [ 7.0 , 6.0 , 5.0 , 4.0 , 3.0 , 4.1 , 5.1 , 4.1 , 6.1 , 6.0 , 6.0 , 6.0 , 6.9 , 6.9 ] # Condiciones monetarias cr = [ 2.0 , 5.0 , 8.0 , 9.0 , 10.0 , 9.0 , 8.0 , 8.0 , 7.0 , 8.1 , 8.1 , 8.1 , 7.1 , 7.1 ] # Riesgo de cr\u00e9dito ra = [ 7.0 , 5.0 , 3.0 , 2.0 , 1.0 , 4.0 , 5.0 , 4.0 , 6.0 , 4.0 , 5.0 , 4.0 , 6.9 , 6.0 ] # Apetito al riesgo In [49]: # Representaci\u00f3n de la serie temporal en formato 'DataFrame' de la libreria 'Pandas' fin_map = pd . DataFrame ( dict ( zip ( riesgos , [ em , cr , ml , mf , ra , mr ])), columns = riesgos , index = ix ) In [51]: # Muestra el gr\u00e1fico y genera un archivo EPS para incluir en el documento. fin_map . plot () sns . set ( style = \"ticks\" ) sns . despine () plt . savefig ( '/home/tony/bm/tfg/source/media/efm.eps' ) In []: if (!document.getElementById('mathjaxscript_pelican_#%@#$@#')) { var mathjaxscript = document.createElement('script'); mathjaxscript.id = 'mathjaxscript_pelican_#%@#$@#'; mathjaxscript.type = 'text/javascript'; mathjaxscript.src = 'https:' == document.location.protocol ? 'https://c328740.ssl.cf1.rackcdn.com/mathjax/latest/MathJax.js?config=TeX-AMS-MML_HTMLorMML' : 'http://cdn.mathjax.org/mathjax/latest/MathJax.js?config=TeX-AMS-MML_HTMLorMML'; mathjaxscript[(window.opera ? \"innerHTML\" : \"text\")] = \"MathJax.Hub.Config({\" + \" config: ['MMLorHTML.js'],\" + \" TeX: { extensions: ['AMSmath.js','AMSsymbols.js','noErrors.js','noUndefined.js'], equationNumbers: { autoNumber: 'AMS' } },\" + \" jax: ['input/TeX','input/MathML','output/HTML-CSS'],\" + \" extensions: ['tex2jax.js','mml2jax.js','MathMenu.js','MathZoom.js'],\" + \" displayAlign: 'center',\" + \" displayIndent: '0em',\" + \" showMathMenu: true,\" + \" tex2jax: { \" + \" inlineMath: [ ['$','$'] ], \" + \" displayMath: [ ['$$','$$'] ],\" + \" processEscapes: true,\" + \" preview: 'TeX',\" + \" }, \" + \" 'HTML-CSS': { \" + \" styles: { '.MathJax_Display, .MathJax .mo, .MathJax .mi, .MathJax .mn': {color: 'black ! important'} }\" + \" } \" + \"}); \"; (document.body || document.getElementsByTagName('head')[0]).appendChild(mathjaxscript); }","tags":"Python","loc":"/my-super-post.html","title":"My super title"}]}